pmdatapipeline_light/__init__.py
pmdatapipeline_light/pmaws.py
pmdatapipeline_light/pmcore.py
pmdatapipeline_light/pmmatillion.py
pmdatapipeline_light/pmtransfer.py
pmdatapipelines/__init__.py
pmdatapipelines/pmaws.py
pmdatapipelines/pmcore.py
pmdatapipelines/pmmatillion.py
pmdatapipelines/pmtransfer.py
pmdatapipelines/pmtransfer_light.py
pmdatapipelines/pmtransform.py
pmdatapipelines-light/__init__.py
pmdatapipelines-light/pmaws.py
pmdatapipelines-light/pmcore.py
pmdatapipelines-light/pmmatillion.py
pmdatapipelines-light/pmtransfer.py
pmdatapipelines_light-0.0.5.dist-info/LICENSE
pmdatapipelines_light-0.0.5.dist-info/METADATA
pmdatapipelines_light-0.0.5.dist-info/WHEEL
pmdatapipelines_light-0.0.5.dist-info/top_level.txt
pmdatapipelines_light-0.0.5.dist-info/RECORD
